LICENSE.txt
MANIFEST.in
pastebin.py
readme.markdown
readme.rst
setup.py
Pastebin.egg-info/PKG-INFO
Pastebin.egg-info/SOURCES.txt
Pastebin.egg-info/dependency_links.txt
Pastebin.egg-info/requires.txt
Pastebin.egg-info/top_level.txt
doc/api-objects.txt
doc/class-tree.html
doc/crarr.png
doc/epydoc.css
doc/epydoc.js
doc/frames.html
doc/help.html
doc/identifier-index.html
doc/index.html
doc/module-tree.html
doc/pastebin-module.html
doc/pastebin-pysrc.html
doc/pastebin.PastebinAPI-class.html
doc/pastebin.PastebinError-class.html
doc/redirect.html
doc/toc-everything.html
doc/toc-pastebin-module.html
doc/toc.html