Metadata-Version: 1.1
Name: Pastebin
Version: 1.1.2
Summary: Python Pastebin API interaction object.
Home-page: http://www.morrolan.com
Author: Ian Havelock
Author-email: ian@morrolan.com
License: GNU General Public License (GPL)
Download-URL: http://pypi.python.org/pypi/Pastebin/
Keywords: pastebin,paste,xml,pastebin API
Platform: Windows
Platform: Unix
Platform: OS X
Classifier: Programming Language :: Python
Classifier: Programming Language :: Python :: 3
Classifier: Development Status :: 4 - Beta
Classifier: Environment :: Other Environment
Classifier: Intended Audience :: Developers
Classifier: Intended Audience :: Education
Classifier: License :: OSI Approved :: GNU General Public License (GPL)
Classifier: Operating System :: OS Independent
Classifier: Topic :: Education
Classifier: Topic :: Software Development :: Libraries :: Python Modules
